wallaroo/__init__.py
wallaroo/_datasizeunit.py
wallaroo/_inference_decode.py
wallaroo/assay.py
wallaroo/assay_config.py
wallaroo/auth.py
wallaroo/client.py
wallaroo/comment.py
wallaroo/config.py
wallaroo/connection.py
wallaroo/continuous_batching_config.py
wallaroo/custom_types.py
wallaroo/deployment.py
wallaroo/deployment_config.py
wallaroo/dynamic_batching_config.py
wallaroo/edge.py
wallaroo/engine_config.py
wallaroo/exceptions.py
wallaroo/framework.py
wallaroo/http_utils.py
wallaroo/model.py
wallaroo/model_config.py
wallaroo/model_registry.py
wallaroo/model_status.py
wallaroo/model_version.py
wallaroo/object.py
wallaroo/openai_config.py
wallaroo/openapi_tmpl.py
wallaroo/orchestration.py
wallaroo/pipeline.py
wallaroo/pipeline_config.py
wallaroo/pipeline_publish.py
wallaroo/pipeline_version.py
wallaroo/queries.py
wallaroo/tag.py
wallaroo/task.py
wallaroo/task_run.py
wallaroo/user.py
wallaroo/user_type.py
wallaroo/utils.py
wallaroo/version.py
wallaroo/visibility.py
wallaroo/workspace.py
wallaroo/assays_v2/__init__.py
wallaroo/assays_v2/assay_result_v2.py
wallaroo/assays_v2/assay_v2.py
wallaroo/assays_v2/assay_v2_builder.py
wallaroo/assays_v2/baseline.py
wallaroo/assays_v2/preview_result.py
wallaroo/assays_v2/scheduling.py
wallaroo/assays_v2/summarizer.py
wallaroo/assays_v2/targeting.py
wallaroo/assays_v2/window.py
wallaroo/records/README.md
wallaroo/records/__init__.py
wallaroo/records/convert_keras_model.py
wallaroo/records/graphql_queries.py
wallaroo/records/telemetry_body.py
wallaroo/records/telemetry_error.py
wallaroo/records/v1_metric_response.py
wallaroo/records/v1_tls_response.py
wallaroo/wallaroo_ml_ops_api_client/__init__.py
wallaroo/wallaroo_ml_ops_api_client/client.py
wallaroo/wallaroo_ml_ops_api_client/errors.py
wallaroo/wallaroo_ml_ops_api_client/types.py
wallaroo/wallaroo_ml_ops_api_client/api/__init__.py
wallaroo/wallaroo_ml_ops_api_client/api/admin/__init__.py
wallaroo/wallaroo_ml_ops_api_client/api/admin/admin_get_pipeline_external_url.py
wallaroo-2025.2.1.dist-info/METADATA
wallaroo-2025.2.1.dist-info/WHEEL
wallaroo-2025.2.1.dist-info/RECORD
