Metadata-Version: 2.4
Name: wallaroo
Version: 2025.2.1
Summary: Wallaroo.ai model management API client
Project-URL: Homepage, https://www.wallaroo.ai/
Author-email: "Wallaroo.ai" <hello@wallaroo.ai>
License: UNKNOWN
Classifier: Development Status :: 5 - Production/Stable
Classifier: Operating System :: OS Independent
Classifier: Programming Language :: Python :: 3.10
Requires-Python: >=3.10
Requires-Dist: appdirs==1.4.4
Requires-Dist: attrs>=21.3.0
Requires-Dist: gql==3.5.0
Requires-Dist: httpx-retries==0.4.0
Requires-Dist: httpx<0.28.0,>=0.20.0
Requires-Dist: ipython==7.31.1
Requires-Dist: matplotlib==3.7.3
Requires-Dist: numpy==1.26.0
Requires-Dist: openai==1.78.1
Requires-Dist: pandas==2.2.0
Requires-Dist: polars==0.18.15
Requires-Dist: pyarrow==14.0.1
Requires-Dist: pydantic==2.11.7
Requires-Dist: pyjwt==2.4.0
Requires-Dist: python-dateutil==2.8.2
Requires-Dist: pyyaml==6.0.1
Requires-Dist: rich==13.7.1
Requires-Dist: seaborn==0.13.2
Requires-Dist: tenacity==8.0.1
